.coveragerc
.travis.yml
MANIFEST.in
README.rst
bootstrap.py
buildout.cfg
setup.cfg
setup.py
travis.cfg
.tx/config
docs/HISTORY.rst
docs/INSTALL.txt
docs/LICENSE.GPL
docs/LICENSE.txt
quintagroup/__init__.py
quintagroup.plonetabs.egg-info/PKG-INFO
quintagroup.plonetabs.egg-info/SOURCES.txt
quintagroup.plonetabs.egg-info/dependency_links.txt
quintagroup.plonetabs.egg-info/entry_points.txt
quintagroup.plonetabs.egg-info/namespace_packages.txt
quintagroup.plonetabs.egg-info/not-zip-safe
quintagroup.plonetabs.egg-info/requires.txt
quintagroup.plonetabs.egg-info/top_level.txt
quintagroup/plonetabs/__init__.py
quintagroup/plonetabs/config.py
quintagroup/plonetabs/configure.zcml
quintagroup/plonetabs/interfaces.py
quintagroup/plonetabs/overrides.zcml
quintagroup/plonetabs/profiles.zcml
quintagroup/plonetabs/rebuild_i18n.sh
quintagroup/plonetabs/setuphandlers.py
quintagroup/plonetabs/utils.py
quintagroup/plonetabs/Extensions/Install.py
quintagroup/plonetabs/Extensions/__init__.py
quintagroup/plonetabs/browser/__init__.py
quintagroup/plonetabs/browser/configure.zcml
quintagroup/plonetabs/browser/interfaces.py
quintagroup/plonetabs/browser/plonetabs.py
quintagroup/plonetabs/browser/resources.zcml
quintagroup/plonetabs/browser/images/busy_icon.gif
quintagroup/plonetabs/browser/images/drag.gif
quintagroup/plonetabs/browser/images/plonetabs.gif
quintagroup/plonetabs/browser/images/trash.gif
quintagroup/plonetabs/browser/images/treeCollapsed.gif
quintagroup/plonetabs/browser/images/treeExpanded.gif
quintagroup/plonetabs/browser/resources/dragdropreorder.js
quintagroup/plonetabs/browser/resources/plonetabs.css
quintagroup/plonetabs/browser/resources/plonetabs.js
quintagroup/plonetabs/browser/templates/actionslist.pt
quintagroup/plonetabs/browser/templates/autogenerated.pt
quintagroup/plonetabs/browser/templates/autogeneratedlist.pt
quintagroup/plonetabs/browser/templates/changemodelink.pt
quintagroup/plonetabs/browser/templates/plonetabs.pt
quintagroup/plonetabs/browser/templates/plonetabs_header_macro.pt
quintagroup/plonetabs/browser/templates/sections.pt
quintagroup/plonetabs/locales/manual.pot
quintagroup/plonetabs/locales/quintagroup.plonetabs.pot
quintagroup/plonetabs/locales/da/LC_MESSAGES/quintagroup.plonetabs.po
quintagroup/plonetabs/locales/fr/LC_MESSAGES/quintagroup.plonetabs.po
