Metadata-Version: 1.0
Name: quintagroup.plonetabs
Version: 1.0
Summary: Quintagroup Plone Tabs
Home-page: http://quintagroup.com/services/plone-development/products/plone-tabs
Author: "Quintagroup": http://quintagroup.com/
Author-email: support@quintagroup.com
License: GPL
Keywords: quintagroup plonetabs
Platform: UNKNOWN
Classifier: Development Status :: 5 - Production/Stable
Classifier: Environment :: Web Environment
Classifier: Framework :: Plone
Classifier: Framework :: Plone :: 3.2
Classifier: Framework :: Plone :: 3.3
Classifier: Framework :: Plone :: 4.0
Classifier: Framework :: Plone :: 4.1
Classifier: Framework :: Plone :: 4.2
Classifier: Framework :: Plone :: 4.3
Classifier: Framework :: Zope2
Classifier: Framework :: Zope3
Classifier: License :: OSI Approved :: GNU General Public License (GPL)
Classifier: Operating System :: OS Independent
Classifier: Programming Language :: Python
Classifier: Topic :: Security
Classifier: Topic :: Software Development :: Libraries :: Python Modules
